Core/__init__.py
Core/griffin_vision.py
Core/__Engines/__init__.py
Core/__Engines/image_embeddings.py
Core/__Engines/text_embeddings.py
Core/__VectorStores/__init__.py
Core/__VectorStores/qdrantvectorstore.py
griffin_vision-0.0.0.dist-info/METADATA
griffin_vision-0.0.0.dist-info/WHEEL
griffin_vision-0.0.0.dist-info/top_level.txt
griffin_vision-0.0.0.dist-info/RECORD
