Metadata-Version: 2.1
Name: griffin-vision
Version: 0.0.0
Summary: A package for performing text-to-image and image-to-image searches using embedding-based techniques
Home-page: https://github.com/junaidbashir11/griffin
Author: JunaidBashir
Author-email: junaidkernel@gmail.com
Classifier: Programming Language :: Python :: 3
Classifier: License :: OSI Approved :: MIT License
Classifier: Operating System :: OS Independent
Requires-Dist: qdrant-client ==1.11.1
Requires-Dist: transformers ==4.44.2
Requires-Dist: requests ==2.32.3
Requires-Dist: torch ==2.4.1
